jpxtime3/__init__.py
jpxtime3/__main__.py
jpxtime3/holiday_jpx.pickle4
jpxtime3/sq.pickle4
jpxtime3-0.0.7.dist-info/METADATA
jpxtime3-0.0.7.dist-info/WHEEL
jpxtime3-0.0.7.dist-info/top_level.txt
jpxtime3-0.0.7.dist-info/RECORD
