Metadata-Version: 2.1
Name: jpxtime3
Version: 0.0.7
Summary: Japan Exchange Delivatives(Index) trading schedule and trading hours
Home-page: UNKNOWN
Author: driller
License: UNKNOWN
Platform: UNKNOWN
Requires-Dist: python-dateutil
